fnet_sitemapper/__init__.py
fnet_sitemapper/cli/__init__.py
fnet_sitemapper/cli/index.py
fnet_sitemapper/lib/__init__.py
fnet_sitemapper/lib/index.py
fnet_sitemapper-0.1.1.dist-info/METADATA
fnet_sitemapper-0.1.1.dist-info/WHEEL
fnet_sitemapper-0.1.1.dist-info/entry_points.txt
fnet_sitemapper-0.1.1.dist-info/top_level.txt
fnet_sitemapper-0.1.1.dist-info/RECORD
